esc/__init__.py
esc/__main__.py
esc/builtin_stubs.py
esc/commands.py
esc/consts.py
esc/display.py
esc/functest.py
esc/function_loader.py
esc/functions.py
esc/helpme.py
esc/history.py
esc/modes.py
esc/oops.py
esc/registers.py
esc/stack.py
esc/status.py
esc/util.py
esc_calc-1.0.0.data/scripts/esc
tests/__init__.py
tests/esc/__init__.py
tests/esc/test_functest.py
tests/esc/test_functest_adapter.py
tests/esc/test_helpme.py
tests/esc/test_history.py
tests/esc/test_registry.py
tests/esc/test_stackitem.py
tests/esc/test_stackstate.py
tests/esc/test_util.py
esc_calc-1.0.0.dist-info/LICENSE
esc_calc-1.0.0.dist-info/METADATA
esc_calc-1.0.0.dist-info/WHEEL
esc_calc-1.0.0.dist-info/top_level.txt
esc_calc-1.0.0.dist-info/RECORD
