Metadata-Version: 2.1
Name: esc-calc
Version: 1.0.0
Summary: extensible stack-based RPN calculator based on curses
Home-page: https://github.com/sobjornstad/esc
Author: Soren I. Bjornstad
Author-email: contact@sorenbjornstad.com
License: UNKNOWN
Platform: UNKNOWN
Classifier: Programming Language :: Python :: 3
Classifier: Programming Language :: Python :: 3.6
Classifier: Programming Language :: Python :: 3.7
Classifier: License :: OSI Approved :: GNU General Public License v3 (GPLv3)
Classifier: Operating System :: OS Independent
Requires-Python: >=3.6
Requires-Dist: windows-curses ; platform_system == "Windows"
